{
  "modo": "simulacion",
  "capital": 97.38,
  "capital_inicial": 100.0,
  "dia_actual": 16,
  "dias_totales": 200,
  "stake_por_juego": 5.125,
  "experimento_activo": true,
  "ultimo_bloqueo": null,
  "dias": [
    {
      "dia": 1,
      "fecha": "2026-07-08",
      "bloqueado_en": "2026-07-08T22:07:46.157856-04:00",
      "apuestas": [
        {
          "game_id": "824496",
          "visitante": "Philadelphia Phillies",
          "home": "Cincinnati Reds",
          "pick": "Cincinnati Reds ML",
          "odds": 2.4,
          "odds_american": 140,
          "lineas_fuente": "betmgm",
          "casa": "BetMGM",
          "edge": 18.5,
          "probPick": 58.2,
          "motivo_apuesta": "Valor +18.5% vs BetMGM (modelo 58% vs mercado 42%)",
          "pitcherAway": "Alan Rangel",
          "pitcherHome": "Chase Burns",
          "inicio_juego": "2026-07-08T19:10:00-04:00",
          "hora_bloqueo_plan": "2026-07-08T18:10:00-04:00",
          "stake": 5.0,
          "estado": "ganada",
          "profit": 7.0,
          "bloqueado_en": "2026-07-08T22:07:46.157856-04:00",
          "marcador_final": "Philadelphia Phillies 5 - Cincinnati Reds 11",
          "liquidado_en": "2026-07-08T22:23:08.848477-04:00"
        },
        {
          "game_id": "823684",
          "visitante": "Cleveland Guardians",
          "home": "Minnesota Twins",
          "pick": "Minnesota Twins ML",
          "odds": 2.1,
          "odds_american": 110,
          "lineas_fuente": "betmgm",
          "casa": "BetMGM",
          "edge": 20.0,
          "probPick": 65.6,
          "motivo_apuesta": "Valor +20.0% vs BetMGM (modelo 66% vs mercado 48%)",
          "pitcherAway": "Slade Cecconi",
          "pitcherHome": "Connor Prielipp",
          "inicio_juego": "2026-07-08T19:40:00-04:00",
          "hora_bloqueo_plan": "2026-07-08T18:40:00-04:00",
          "stake": 5.0,
          "estado": "ganada",
          "profit": 5.5,
          "bloqueado_en": "2026-07-08T22:07:46.799436-04:00",
          "marcador_final": "Cleveland Guardians 5 - Minnesota Twins 6",
          "liquidado_en": "2026-07-08T22:59:15.369723-04:00"
        },
        {
          "game_id": "823928",
          "visitante": "Colorado Rockies",
          "home": "Los Angeles Dodgers",
          "pick": "Colorado Rockies ML",
          "odds": 3.2,
          "odds_american": 220,
          "lineas_fuente": "betmgm",
          "casa": "BetMGM",
          "edge": 28.0,
          "probPick": 57.3,
          "motivo_apuesta": "Valor +28.0% vs BetMGM (modelo 57% vs mercado 31%)",
          "pitcherAway": "Gabriel Hughes",
          "pitcherHome": "Roki Sasaki",
          "inicio_juego": "2026-07-08T22:10:00-04:00",
          "hora_bloqueo_plan": "2026-07-08T21:10:00-04:00",
          "stake": 5.0,
          "estado": "perdida",
          "profit": -5.0,
          "bloqueado_en": "2026-07-08T22:07:49.489725-04:00",
          "marcador_final": "Colorado Rockies 2 - Los Angeles Dodgers 3",
          "liquidado_en": "2026-07-08T22:42:15.474360-04:00"
        },
        {
          "game_id": "823279",
          "visitante": "Arizona Diamondbacks",
          "home": "San Diego Padres",
          "pick": "San Diego Padres ML",
          "odds": 1.769,
          "odds_american": -130,
          "lineas_fuente": "betmgm",
          "casa": "BetMGM",
          "edge": 8.6,
          "probPick": 63.1,
          "motivo_apuesta": "Valor +8.6% vs BetMGM (modelo 63% vs mercado 56%)",
          "pitcherAway": "Jose Cabrera",
          "pitcherHome": "Michael King",
          "inicio_juego": "2026-07-08T22:10:00-04:00",
          "hora_bloqueo_plan": "2026-07-08T21:10:00-04:00",
          "stake": 5.0,
          "estado": "perdida",
          "profit": -5.0,
          "bloqueado_en": "2026-07-08T22:07:50.320320-04:00",
          "marcador_final": "Arizona Diamondbacks 1 - San Diego Padres 0",
          "liquidado_en": "2026-07-08T22:23:08.848634-04:00"
        }
      ],
      "resumen": {
        "jugadas": 4,
        "ganadas": 2,
        "perdidas": 2,
        "pendientes": 0,
        "profit_dia": 2.5,
        "capital_arriesgado": 0,
        "total_apostado": 20.0
      },
      "predicciones": []
    },
    {
      "dia": 2,
      "fecha": "2026-07-09",
      "bloqueado_en": "2026-07-09T23:20:35.155792-04:00",
      "apuestas": [
        {
          "game_id": "823277",
          "visitante": "Arizona Diamondbacks",
          "home": "San Diego Padres",
          "pick": "San Diego Padres ML",
          "odds": 2.65,
          "odds_american": 165,
          "lineas_fuente": "betmgm",
          "casa": "BetMGM",
          "edge": 22.3,
          "probPick": 58.0,
          "motivo_apuesta": "Valor +22.3% vs BetMGM (modelo 58% vs mercado 38%)",
          "pitcherAway": "Merrill Kelly",
          "pitcherHome": "Griffin Canning",
          "inicio_juego": "2026-07-09T21:40:00-04:00",
          "hora_bloqueo_plan": "2026-07-09T20:40:00-04:00",
          "stake": 5.125,
          "estado": "perdida",
          "profit": -5.12,
          "bloqueado_en": "2026-07-09T23:20:35.155792-04:00",
          "marcador_final": "Arizona Diamondbacks 3 - San Diego Padres 1",
          "liquidado_en": "2026-07-09T23:51:36.251397-04:00"
        }
      ],
      "predicciones": [
        {
          "game_id": "824251",
          "visitante": "Athletics",
          "home": "Detroit Tigers",
          "pick": "Detroit Tigers ML",
          "odds": 1.01,
          "odds_american": -10000,
          "edge": -56.2,
          "probPick": 42.8,
          "motivo_apuesta": "Prob. modelo bajo 54.0%",
          "pitcherAway": "José Suarez",
          "pitcherHome": "Framber Valdez",
          "inicio_juego": "2026-07-09T18:40:00-04:00",
          "estado": "liquidado",
          "resultado": "acierto",
          "predicho_en": "2026-07-09T20:59:34.593850-04:00",
          "marcador_final": "Athletics 1 - Detroit Tigers 4",
          "liquidado_en": "2026-07-09T21:09:33.648732-04:00",
          "profit": 0.05,
          "stake_virtual": 5.0
        },
        {
          "game_id": "823846",
          "visitante": "Seattle Mariners",
          "home": "Miami Marlins",
          "pick": "Miami Marlins ML",
          "odds": 1.01,
          "odds_american": -10000,
          "edge": -60.9,
          "probPick": 38.1,
          "motivo_apuesta": "Prob. modelo bajo 54.0%",
          "pitcherAway": "Bryce Miller",
          "pitcherHome": "Janson Junk",
          "inicio_juego": "2026-07-09T18:40:00-04:00",
          "estado": "liquidado",
          "resultado": "acierto",
          "predicho_en": "2026-07-09T20:59:38.430501-04:00",
          "marcador_final": "Seattle Mariners 4 - Miami Marlins 8",
          "liquidado_en": "2026-07-09T21:09:33.648923-04:00",
          "profit": 0.05,
          "stake_virtual": 5.0
        },
        {
          "game_id": "824494",
          "visitante": "Philadelphia Phillies",
          "home": "Cincinnati Reds",
          "pick": "Cincinnati Reds ML",
          "odds": 4.5,
          "odds_american": 350,
          "edge": 13.5,
          "probPick": 35.7,
          "motivo_apuesta": "Prob. modelo bajo 54.0%",
          "pitcherAway": "Jesús Luzardo",
          "pitcherHome": "Brady Singer",
          "inicio_juego": "2026-07-09T19:10:00-04:00",
          "estado": "liquidado",
          "resultado": "fallo",
          "predicho_en": "2026-07-09T20:59:42.433061-04:00",
          "marcador_final": "Philadelphia Phillies 1 - Cincinnati Reds 0",
          "liquidado_en": "2026-07-09T21:09:33.649066-04:00",
          "profit": -5.0,
          "stake_virtual": 5.0
        },
        {
          "game_id": "823034",
          "visitante": "Milwaukee Brewers",
          "home": "St. Louis Cardinals",
          "pick": "Milwaukee Brewers ML",
          "odds": 1.02,
          "odds_american": -5000,
          "edge": -62.4,
          "probPick": 35.6,
          "motivo_apuesta": "Prob. modelo bajo 54.0%",
          "pitcherAway": "Logan Henderson",
          "pitcherHome": "Andre Pallante",
          "inicio_juego": "2026-07-09T19:45:00-04:00",
          "estado": "liquidado",
          "resultado": "acierto",
          "predicho_en": "2026-07-09T20:59:46.201990-04:00",
          "marcador_final": "Milwaukee Brewers 6 - St. Louis Cardinals 1",
          "liquidado_en": "2026-07-09T21:09:33.649210-04:00",
          "profit": 0.1,
          "stake_virtual": 5.0
        },
        {
          "game_id": "822877",
          "visitante": "Los Angeles Angels",
          "home": "Texas Rangers",
          "pick": "Texas Rangers ML",
          "odds": 1.364,
          "odds_american": -275,
          "edge": -36.1,
          "probPick": 37.2,
          "motivo_apuesta": "Sin valor (mínimo +6.0% edge)",
          "pitcherAway": "Reid Detmers",
          "pitcherHome": "Nathan Eovaldi",
          "inicio_juego": "2026-07-09T20:05:00-04:00",
          "estado": "liquidado",
          "resultado": "acierto",
          "predicho_en": "2026-07-09T20:59:49.994825-04:00",
          "marcador_final": "Los Angeles Angels 1 - Texas Rangers 2",
          "liquidado_en": "2026-07-09T21:09:33.649345-04:00",
          "profit": 1.82,
          "stake_virtual": 5.0
        },
        {
          "game_id": "823277",
          "visitante": "Arizona Diamondbacks",
          "home": "San Diego Padres",
          "pick": "San Diego Padres ML",
          "odds": 1.769,
          "odds_american": -130,
          "edge": -18.3,
          "probPick": 38.2,
          "motivo_apuesta": "Sin valor (mínimo +6.0% edge)",
          "pitcherAway": "Merrill Kelly",
          "pitcherHome": "Griffin Canning",
          "inicio_juego": "2026-07-09T21:40:00-04:00",
          "estado": "liquidado",
          "resultado": "fallo",
          "predicho_en": "2026-07-09T20:59:53.788523-04:00",
          "marcador_final": "Arizona Diamondbacks 3 - San Diego Padres 1",
          "liquidado_en": "2026-07-09T23:51:36.251549-04:00",
          "profit": -5.0,
          "stake_virtual": 5.0
        },
        {
          "game_id": "823201",
          "visitante": "Colorado Rockies",
          "home": "San Francisco Giants",
          "pick": "San Francisco Giants ML",
          "odds": 1.769,
          "odds_american": -130,
          "edge": -20.1,
          "probPick": 36.4,
          "motivo_apuesta": "Sin valor (mínimo +6.0% edge)",
          "pitcherAway": "Ryan Feltner",
          "pitcherHome": "Carson Whisenhunt",
          "inicio_juego": "2026-07-09T21:45:00-04:00",
          "estado": "liquidado",
          "resultado": "acierto",
          "predicho_en": "2026-07-09T20:59:58.117393-04:00",
          "marcador_final": "Colorado Rockies 2 - San Francisco Giants 4",
          "liquidado_en": "2026-07-09T23:51:36.251746-04:00",
          "profit": 3.84,
          "stake_virtual": 5.0
        }
      ],
      "resumen": {
        "jugadas": 1,
        "ganadas": 0,
        "perdidas": 1,
        "pendientes": 0,
        "profit_dia": -5.12,
        "capital_arriesgado": 0,
        "total_apostado": 5.12
      }
    },
    {
      "dia": 3,
      "fecha": "2026-07-10",
      "bloqueado_en": null,
      "apuestas": [],
      "predicciones": [],
      "resumen": {
        "jugadas": 0,
        "ganadas": 0,
        "perdidas": 0,
        "pendientes": 0,
        "profit_dia": 0,
        "capital_arriesgado": 0,
        "total_apostado": 0
      }
    },
    {
      "dia": 4,
      "fecha": "2026-07-11",
      "bloqueado_en": null,
      "apuestas": [],
      "predicciones": [],
      "resumen": {
        "jugadas": 0,
        "ganadas": 0,
        "perdidas": 0,
        "pendientes": 0,
        "profit_dia": 0,
        "capital_arriesgado": 0,
        "total_apostado": 0
      }
    },
    {
      "dia": 5,
      "fecha": "2026-07-12",
      "bloqueado_en": null,
      "apuestas": [],
      "predicciones": [],
      "resumen": {
        "jugadas": 0,
        "ganadas": 0,
        "perdidas": 0,
        "pendientes": 0,
        "profit_dia": 0,
        "capital_arriesgado": 0,
        "total_apostado": 0
      }
    },
    {
      "dia": 6,
      "fecha": "2026-07-13",
      "bloqueado_en": null,
      "apuestas": [],
      "predicciones": [],
      "resumen": {
        "jugadas": 0,
        "ganadas": 0,
        "perdidas": 0,
        "pendientes": 0,
        "profit_dia": 0,
        "capital_arriesgado": 0,
        "total_apostado": 0
      }
    },
    {
      "dia": 7,
      "fecha": "2026-07-14",
      "bloqueado_en": null,
      "apuestas": [],
      "predicciones": [],
      "resumen": {
        "jugadas": 0,
        "ganadas": 0,
        "perdidas": 0,
        "pendientes": 0,
        "profit_dia": 0,
        "capital_arriesgado": 0,
        "total_apostado": 0
      }
    },
    {
      "dia": 8,
      "fecha": "2026-07-15",
      "bloqueado_en": null,
      "apuestas": [],
      "predicciones": [],
      "resumen": {
        "jugadas": 0,
        "ganadas": 0,
        "perdidas": 0,
        "pendientes": 0,
        "profit_dia": 0,
        "capital_arriesgado": 0,
        "total_apostado": 0
      }
    },
    {
      "dia": 9,
      "fecha": "2026-07-16",
      "bloqueado_en": null,
      "apuestas": [],
      "predicciones": [],
      "resumen": {
        "jugadas": 0,
        "ganadas": 0,
        "perdidas": 0,
        "pendientes": 0,
        "profit_dia": 0,
        "capital_arriesgado": 0,
        "total_apostado": 0
      }
    },
    {
      "dia": 10,
      "fecha": "2026-07-17",
      "bloqueado_en": null,
      "apuestas": [],
      "predicciones": [],
      "resumen": {
        "jugadas": 0,
        "ganadas": 0,
        "perdidas": 0,
        "pendientes": 0,
        "profit_dia": 0,
        "capital_arriesgado": 0,
        "total_apostado": 0
      }
    },
    {
      "dia": 11,
      "fecha": "2026-07-18",
      "bloqueado_en": null,
      "apuestas": [],
      "predicciones": [
        {
          "game_id": "824979",
          "visitante": "Washington Nationals",
          "home": "Athletics",
          "pick": "Washington Nationals ML",
          "odds": 1.608,
          "odds_american": -164,
          "edge": 12.2,
          "probPick": 62.2,
          "motivo_apuesta": "Modelo 62% (solo stats+ML, sin BetMGM)",
          "pitcherAway": "Zack Littell",
          "pitcherHome": "J.T. Ginn",
          "inicio_juego": "2026-07-18T22:05:00-04:00",
          "estado": "pendiente",
          "resultado": null,
          "profit": null,
          "stake_virtual": 5.125,
          "con_dinero": false,
          "predicho_en": "2026-07-18T23:31:37.104173-04:00"
        },
        {
          "game_id": "824008",
          "visitante": "Detroit Tigers",
          "home": "Los Angeles Angels",
          "pick": "Los Angeles Angels ML",
          "odds": 1.5,
          "odds_american": 150,
          "edge": 0,
          "probPick": 52.8,
          "motivo_apuesta": "Prob. modelo bajo 58.0%",
          "pitcherAway": "Tarik Skubal",
          "pitcherHome": "Grayson Rodriguez",
          "inicio_juego": "2026-07-18T22:07:00-04:00",
          "estado": "pendiente",
          "resultado": null,
          "profit": null,
          "stake_virtual": 5.125,
          "con_dinero": false,
          "predicho_en": "2026-07-18T23:31:37.104212-04:00"
        }
      ],
      "resumen": {
        "jugadas": 0,
        "ganadas": 0,
        "perdidas": 0,
        "pendientes": 0,
        "profit_dia": 0,
        "capital_arriesgado": 0,
        "total_apostado": 0
      }
    },
    {
      "dia": 12,
      "fecha": "2026-07-19",
      "apuestas": [],
      "predicciones": [],
      "bloqueado_en": null
    },
    {
      "dia": 13,
      "fecha": "2026-07-20",
      "apuestas": [],
      "predicciones": [],
      "bloqueado_en": null
    },
    {
      "dia": 14,
      "fecha": "2026-07-21",
      "apuestas": [],
      "predicciones": [],
      "bloqueado_en": null
    },
    {
      "dia": 15,
      "fecha": "2026-07-22",
      "apuestas": [],
      "predicciones": [],
      "bloqueado_en": null
    },
    {
      "dia": 16,
      "fecha": "2026-07-23",
      "apuestas": [],
      "predicciones": [
        {
          "game_id": "824893",
          "visitante": "San Diego Padres",
          "home": "Atlanta Braves",
          "pick": "Atlanta Braves ML",
          "odds": 1.326,
          "odds_american": -307,
          "edge": 25.4,
          "probPick": 75.4,
          "motivo_apuesta": "Modelo 75% (solo stats+ML, sin BetMGM)",
          "pitcherAway": "Kyle Hart",
          "pitcherHome": "Chris Sale",
          "inicio_juego": "2026-07-23T12:15:00-04:00",
          "estado": "liquidado",
          "resultado": "acierto",
          "profit": 1.63,
          "stake_virtual": 5.0,
          "con_dinero": false,
          "predicho_en": "2026-07-23T21:04:49.967088-04:00",
          "retroactivo": true,
          "marcador_final": "San Diego Padres 5 - Atlanta Braves 6",
          "liquidado_en": "2026-07-23T21:09:08.161764-04:00"
        },
        {
          "game_id": "824406",
          "visitante": "Minnesota Twins",
          "home": "Cleveland Guardians",
          "pick": "Minnesota Twins ML",
          "odds": 1.5,
          "odds_american": 150,
          "edge": 0,
          "probPick": 50.1,
          "motivo_apuesta": "Prob. modelo bajo 58.0%",
          "pitcherAway": "Taj Bradley",
          "pitcherHome": "Gavin Williams",
          "inicio_juego": "2026-07-23T13:10:00-04:00",
          "estado": "liquidado",
          "resultado": "acierto",
          "profit": 2.5,
          "stake_virtual": 5.0,
          "con_dinero": false,
          "predicho_en": "2026-07-23T21:04:49.967743-04:00",
          "retroactivo": true,
          "marcador_final": "Minnesota Twins 3 - Cleveland Guardians 1",
          "liquidado_en": "2026-07-23T21:09:08.161950-04:00"
        },
        {
          "game_id": "822785",
          "visitante": "Tampa Bay Rays",
          "home": "Toronto Blue Jays",
          "pick": "Toronto Blue Jays ML",
          "odds": 1.5,
          "odds_american": 150,
          "edge": 0,
          "probPick": 54.0,
          "motivo_apuesta": "Prob. modelo bajo 58.0%",
          "pitcherAway": "Casey Legumina",
          "pitcherHome": "Shane Bieber",
          "inicio_juego": "2026-07-23T15:07:00-04:00",
          "estado": "liquidado",
          "resultado": "acierto",
          "profit": 2.5,
          "stake_virtual": 5.0,
          "con_dinero": false,
          "predicho_en": "2026-07-23T21:04:49.969224-04:00",
          "retroactivo": true,
          "marcador_final": "Tampa Bay Rays 1 - Toronto Blue Jays 3",
          "liquidado_en": "2026-07-23T21:09:08.162042-04:00"
        },
        {
          "game_id": "823042",
          "visitante": "Arizona Diamondbacks",
          "home": "St. Louis Cardinals",
          "pick": "Arizona Diamondbacks ML",
          "odds": 1.5,
          "odds_american": 150,
          "edge": 0,
          "probPick": 51.1,
          "motivo_apuesta": "Prob. modelo bajo 58.0%",
          "pitcherAway": "Brandon Pfaadt",
          "pitcherHome": "Michael McGreevy",
          "inicio_juego": "2026-07-23T17:15:00-04:00",
          "estado": "liquidado",
          "resultado": "acierto",
          "profit": 2.5,
          "stake_virtual": 5.0,
          "con_dinero": false,
          "predicho_en": "2026-07-23T21:04:49.969443-04:00",
          "retroactivo": true,
          "marcador_final": "Arizona Diamondbacks 10 - St. Louis Cardinals 6",
          "liquidado_en": "2026-07-23T21:09:08.162166-04:00"
        },
        {
          "game_id": "824247",
          "visitante": "Kansas City Royals",
          "home": "Detroit Tigers",
          "pick": "Kansas City Royals ML",
          "odds": 1.5,
          "odds_american": 150,
          "edge": 0,
          "probPick": 53.5,
          "motivo_apuesta": "Prob. modelo bajo 58.0%",
          "pitcherAway": "Randy Dobnak",
          "pitcherHome": "Troy Melton",
          "inicio_juego": "2026-07-23T18:40:00-04:00",
          "estado": "pendiente",
          "resultado": null,
          "profit": null,
          "stake_virtual": 5.0,
          "con_dinero": false,
          "predicho_en": "2026-07-23T21:04:50.071068-04:00",
          "retroactivo": true
        }
      ],
      "bloqueado_en": null
    }
  ],
  "ml_meta": {
    "ok": true,
    "muestras": 12,
    "mensaje": "Reentrenado con 12 muestras (acc 91.7%)",
    "accuracy_train": 0.917,
    "ultimo_entreno": "2026-07-17T23:15:50.473749",
    "recuperacion": {
      "fecha": "2026-07-24T01:22:05.956989Z",
      "fuente": "git+live_2026-07-23",
      "nota": "Historial post 18-jul (excepto hoy) no estaba en backup; no recuperable sin copia de Render.",
      "papel": "9✓/2✗",
      "dinero": "2✓/3✗"
    }
  }
}
